{
  "_description": "Example extracted All Fields Detail data from MLS 22610267, a real listing on Paragon Connect. Use this as the reference shape for scraped listing data.",
  "_mls_source": "22610267",
  "_field_count": 138,
  "fields": {
    "MLS #": "22610267",
    "Status": "New",
    "Class": "RESIDENTIAL",
    "Listing Price": "$335,000",
    "Property Subtype": "Single Family Residence",
    "Address": "3503 S 152nd Street",
    "County": "Douglas",
    "City": "Omaha",
    "Zip": "68144",
    "State": "Nebraska",
    "VOW Include": "Yes",
    "VOW Address": "Yes",
    "VOW Comment": "Yes",
    "VOW AVM": "Yes",
    "Parcel Number": "1865570000",
    "Listing Agent": "Jenna Jacupke",
    "Listing Office": "BHHS Ambassador Real Estate - 4300",
    "Subdivision": "OAKBROOK MEADOWS",
    "List Date": "04/16/2026",
    "Occupant Type": "Owner",
    "SID Y/N": "No",
    "HOA (Y/N)": "No",
    "Directions to Property": "Consult GPS",
    "Lot Dimension Source": "Assessor",
    "Lot Dimensions": "126x80",
    "Total Acres": "0.230",
    "Bedrooms": "3",
    "Bedrooms Above Grade": "3",
    "Bathrooms": "3",
    "# of Fireplaces": "1",
    "Garage Spaces": "2",
    "Square Footage Source": "Other",
    "Main Floor SqFt": "1,248",
    "2nd Floor SqFt": "0",
    "3rd Floor SqFt": "0",
    "4th Floor SqFt": "0",
    "Basement": "Yes",
    "Finished Basement": "350",
    "Total Basement SqFt": "1,092",
    "Total Finished Below Grade": "350",
    "Above Grade SQFT": "1,248",
    "Total Finished SqFt": "1,598",
    "Price Per SQFT AG": "$268.43",
    "Price per SQFT Total": "209.64",
    "Property Attached Y/N": "No",
    "Tax Amount": "$4,673.38",
    "Taxes (Partial/Full)": "Full",
    "Tax Year": "2025",
    "Year Built": "1992",
    "New Construction": "Not New and NOT a Model",
    "Lot Size Range": "Up to 1/4 Acre.",
    "Grade School": "Willa Cather",
    "Jr. High School": "Millard Central",
    "High School": "Millard North",
    "Style": "Split Entry",
    "Agreement Type": "Exclusive Right to Sell",
    "Non Standard Form": "No",
    "Agent Has Equity": "No",
    "Dining Room Formal Size": "13.2 x 9.9",
    "Dining Room Formal Level": "Main Floor",
    "Kitchen Size": "18 x 9.7",
    "Kitchen Level": "Main Floor",
    "Family Room Size": "17 x 13.6",
    "Family Room Level": "Main Floor",
    "Rec Room Size": "15 x 11",
    "Rec Room Level": "Basement",
    "Primary Bedroom Size": "14.9 x 11.2",
    "Primary Bedroom Level": "Main Floor",
    "Bedroom #2 Size": "10 x 11.4",
    "Bedroom #2 Level": "Main Floor",
    "Bedroom #3 Size": "10 x 10",
    "Bedroom #3 Level": "Main Floor",
    "Laundry Room Level": "Basement",
    "3rd Floor Baths": "////",
    "2nd Floor Baths": "////",
    "Main Floor Baths": "2/0/0/0/0",
    "Main Floor Full Baths": "2",
    "Main Floor 3/4 Baths": "0",
    "Main Floor 1/2 Baths": "0",
    "Main Floor 1/4 Baths": "0",
    "Main Floor Rough-In": "0",
    "Below Grade Baths": "0/0/1/0/0",
    "Below Grade Full Baths": "0",
    "Below Grade 3/4 Baths": "0",
    "Below Grade 1/2 Baths": "1",
    "Below Grade 1/4 Baths": "0",
    "Below Grade Rough-In": "0",
    "Client Hit Count": "5",
    "Agent Hit Count": "24",
    "REO (Bank, ETC, OWNED)Y/N": "NO",
    "IDX Include": "Yes",
    "Update Date": "04/19/2026",
    "Status Date": "04/16/2026",
    "HotSheet Date": "04/16/2026",
    "Price Date": "04/16/2026",
    "Input Date": "04/16/2026",
    "General Date": "04/16/2026",
    "Associated Document Count": "1",
    "Original Price": "$335,000",
    "Lock Box Provider": "Supra",
    "Showing Contact Type": "Showing Service",
    "COOLING": "Central Air",
    "EXTERIOR FEATURES": "Deck/Balcony",
    "FENCE": "Full",
    "GARAGE TYPE": "Attached",
    "HEATING FUEL": "Gas",
    "HEATING TYPE": "Forced Air",
    "OWNERSHIP TYPE": "Fee Simple",
    "SEWER AND WATER": "Public Sewer, Public Water",
    "FINANCING TERMS ACCEPTED": "Cash, Conventional, FHA, VA",
    "BASEMENT TYPE": "Partial",
    "FOUNDATION DETAILS": "Concrete Block",
    "Agent Remarks": "AMA. For any questions regarding the property, please call Jenna Jacupke at (402) 416-8366? Email offers to Jenna.jacupke@bhhsamb.com. sellers ideal closing first week in June.",
    "Public Remarks": "Well-maintained 3 bed, 3 bath home on a spacious corner lot! This inviting property features a 2-car garage, fenced backyard, and multiple outdoor living spaces including a deck and patio\u2014perfect for relaxing or entertaining. Thoughtfully updated throughout (2023-garage door, interior paint 2024- New Windows/LVP flooring 2025-Exterior Paint)  this home offers comfort, functionality, and pride of ownership in every detail. A must-see opportunity!",
    "Showing Instructions": "For any questions regarding the property, please call Jenna Jacupke at (402) 416-8366?",
    "Propensity to Sell Score:": "Listed",
    "Estimated Loan to Value:": "76%",
    "Estimated Equity:": "$74,622",
    "Current Owner": "Perry Alexander",
    "Mailing Address": "3503 S 152nd St Omaha NE 68144-5515",
    "Tax ID": "1865570000",
    "Subdivision (2)": "Oakbrook Meadows",
    "Property Type": "Residential",
    "Zoning": "R4",
    "County (2)": "DOUGLAS",
    "Lot Size": "10080 SF",
    "Lot": "269",
    "Longitude/Latitude": "-96.15127563476562 / 41.22428512573242",
    "Legal Description": "Oakbrook Meadows Lot 269 Block 0 Irreg",
    "Bedrooms (2)": "3",
    "Year Built (2)": "1992",
    "Air Conditioning": "Central",
    "Total Square Feet": "1226",
    "Bathrooms Full/Half": "2/0",
    "Stories": "1",
    "Exterior Wall": "Wood Siding",
    "Heat Type": "Central",
    "Tax ID (2)": "1865570000"
  }
}